yellow_idea_py/__init__.py
yellow_idea_py/aws_s3_upload.py
yellow_idea_py/crud.py
yellow_idea_py/global_controller_cms.py
yellow_idea_py/global_model_core.py
yellow_idea_py/global_model_line.py
yellow_idea_py/helper.py
yellow_idea_py/middleware.py
yellow_idea_py/mysql.py
yellow_idea_py-0.3.3.dist-info/LICENSE
yellow_idea_py-0.3.3.dist-info/METADATA
yellow_idea_py-0.3.3.dist-info/WHEEL
yellow_idea_py-0.3.3.dist-info/top_level.txt
yellow_idea_py-0.3.3.dist-info/RECORD
