Metadata-Version: 2.1
Name: yellow-idea-py
Version: 0.3.3
Summary: Yellow Idea SDK
Home-page: UNKNOWN
Author: Kittiphong Jittanupagorn
Author-email: ragnarokmaster03@gmail.com
License: UNKNOWN
Platform: UNKNOWN
